mgl_formulae/__init__.py
mgl_formulae/__main__.py
mgl_formulae/__version__.py
mgl_formulae/compile.py
mgl_formulae/formulae.lark
mgl_formulae/grammar.py
mgl_formulae/rebuild.py
mgl_formulae/rules.py
mgl_formulae-0.1.0.dist-info/LICENSE
mgl_formulae-0.1.0.dist-info/METADATA
mgl_formulae-0.1.0.dist-info/WHEEL
mgl_formulae-0.1.0.dist-info/RECORD
