Metadata-Version: 2.1
Name: mgl-formulae
Version: 0.1.0
Summary: Conversion to/from a human-oriented formula representation for mapbox-gl expression language
Home-page: https://github.com/himikof/mgl-formulae
License: Apache-2.0
Author: Nikita Ofitserov
Author-email: himikof@gmail.com
Requires-Python: >=3.7
Classifier: License :: OSI Approved :: Apache Software License
Classifier: Programming Language :: Python :: 3
Classifier: Programming Language :: Python :: 3.7
Classifier: Programming Language :: Python :: 3.8
Classifier: Programming Language :: Python :: 3.9
Classifier: Programming Language :: Python :: 3.10
Classifier: Programming Language :: Python :: 3.11
Classifier: Topic :: Scientific/Engineering :: GIS
Classifier: Topic :: Software Development :: Compilers
Requires-Dist: lark (>=1.1.4,<2.0.0)
Project-URL: Repository, https://github.com/himikof/mgl-formulae
